csv_to_xlsx/__init__.py
csv_to_xlsx/convert.py
csv_to_xlsx-0.0.5.dist-info/METADATA
csv_to_xlsx-0.0.5.dist-info/RECORD
csv_to_xlsx-0.0.5.dist-info/WHEEL
csv_to_xlsx-0.0.5.dist-info/top_level.txt
