Metadata-Version: 2.1
Name: csv-to-xlsx
Version: 0.0.5
Summary: Convert CSV and TSV to XLSX files using openpyxl
Home-page: https://github.com/russlamb/file_convert
Author: Russ Lamb
Author-email: revoltingrobot@gmail.com
License: UNKNOWN
Platform: UNKNOWN
Classifier: Programming Language :: Python :: 3
Classifier: License :: OSI Approved :: MIT License
Classifier: Operating System :: OS Independent
Requires-Dist: openpyxl
